CommandTracker/__init__.py
CommandTracker/cli.py
CommandTracker/core.py
CommandTracker/graph.py
CommandTracker/history.py
CommandTracker/monitor.py
CommandTracker/utils.py
CommandTracker-0.1.5.dist-info/LICENSE
CommandTracker-0.1.5.dist-info/METADATA
CommandTracker-0.1.5.dist-info/WHEEL
CommandTracker-0.1.5.dist-info/entry_points.txt
CommandTracker-0.1.5.dist-info/top_level.txt
CommandTracker-0.1.5.dist-info/RECORD
