Metadata-Version: 2.1
Name: CommandTracker
Version: 0.1.5
Summary: Paquete para ejecutar comandos y monitorear uso de CPU y memoria
Home-page: https://github.com/ErickCosta98/CommandTracker
Author: Erick Costa
Author-email: erickhcosta98@gmail.com
Classifier: Programming Language :: Python :: 3
Classifier: License :: OSI Approved :: MIT License
Classifier: Operating System :: OS Independent
Requires-Python: >=3.6
License-File: LICENSE
Requires-Dist: psutil
Requires-Dist: plotext
